ansys/chemkin/__init__.py
ansys/chemkin/chemistry.py
ansys/chemkin/chemkin_wrapper.py
ansys/chemkin/color.py
ansys/chemkin/constants.py
ansys/chemkin/flame.py
ansys/chemkin/grid.py
ansys/chemkin/hybridreactornetwork.py
ansys/chemkin/info.py
ansys/chemkin/inlet.py
ansys/chemkin/logger.py
ansys/chemkin/mixture.py
ansys/chemkin/reactormodel.py
ansys/chemkin/realgaseos.py
ansys/chemkin/steadystatesolver.py
ansys/chemkin/utilities.py
ansys/chemkin/batchreactors/batchreactor.py
ansys/chemkin/data/ChemkinKeywordTips.yaml
ansys/chemkin/engines/HCCI.py
ansys/chemkin/engines/SI.py
ansys/chemkin/engines/engine.py
ansys/chemkin/flowreactors/PFR.py
ansys/chemkin/premixedflames/premixedflame.py
ansys/chemkin/stirreactors/PSR.py
ansys/chemkin/stirreactors/openreactor.py
ansys_chemkin-2025.2.1.dist-info/licenses/LICENSE
ansys_chemkin-2025.2.1.dist-info/WHEEL
ansys_chemkin-2025.2.1.dist-info/METADATA
ansys_chemkin-2025.2.1.dist-info/RECORD
