Metadata-Version: 2.4
Name: ansys-chemkin
Version: 2025.2.1
Summary: PyChemkin provides Pythonic interface to Ansys chemkin utilities and reactor models
Author-email: "ANSYS, Inc." <pyansys.core@ansys.com>
Maintainer-email: "ANSYS, Inc." <pyansys.core@ansys.com>
Requires-Python: >=3.9,<4
Classifier: Development Status :: 4 - Beta
Classifier: Intended Audience :: Science/Research
Classifier: Programming Language :: Python :: 3
Classifier: License :: OSI Approved :: MIT License
Classifier: Operating System :: Microsoft :: Windows :: Windows 11
Classifier: Operating System :: Microsoft :: Windows :: Windows 10
Classifier: Natural Language :: English
License-File: LICENSE
Requires-Dist: numpy>=1.14.0,<3.0.0
Requires-Dist: pyyaml>=6.0
Requires-Dist: matplotlib==3.9.4
Requires-Dist: ansys-sphinx-theme==1.0.11 ; extra == "doc"
Requires-Dist: sphinx-autoapi==3.6.1 ; extra == "doc"
Requires-Dist: matplotlib==3.9.4 ; extra == "doc"
Requires-Dist: jupytext==1.18.1 ; extra == "doc"
Requires-Dist: notebook==7.5.0 ; extra == "doc"
Requires-Dist: nbsphinx==0.9.8 ; extra == "doc"
Requires-Dist: numpydoc==1.9.0 ; extra == "doc"
Requires-Dist: pandas==2.3.3 ; extra == "doc"
Requires-Dist: pandoc==2.4.0 ; extra == "doc"
Requires-Dist: Pillow==11.3.0 ; extra == "doc"
Requires-Dist: PyGitHub==2.8.1 ; extra == "doc"
Requires-Dist: pyvista==0.46.4 ; extra == "doc"
Requires-Dist: requests==2.32.5 ; extra == "doc"
Requires-Dist: sphinx-copybutton==0.5.2 ; extra == "doc"
Requires-Dist: sphinx-design==0.6.1 ; extra == "doc"
Requires-Dist: sphinx-gallery==0.19.0 ; extra == "doc"
Requires-Dist: sphinx-jinja==2.0.2 ; extra == "doc"
Requires-Dist: sphinx-notfound-page==1.1.0 ; extra == "doc"
Requires-Dist: pytest==8.4.2 ; extra == "tests"
Requires-Dist: pytest-cov==7.0.0 ; extra == "tests"
Requires-Dist: dill==0.4.0 ; extra == "tests"
Requires-Dist: pytest-mock==3.15.1 ; extra == "tests"
Requires-Dist: urllib3==2.6.0 ; extra == "tests"
Requires-Dist: requests==2.32.5 ; extra == "tests"
Requires-Dist: docker==7.1.0 ; extra == "tests"
Requires-Dist: usd-core>=24.11 ; extra == "tests"
Requires-Dist: pygltflib==1.16.5 ; extra == "tests"
Requires-Dist: matplotlib==3.9.4 ; extra == "tests"
Requires-Dist: numpy>=1.14.0,<3.0.0 ; extra == "tests"
Requires-Dist: pyyaml>=6.0 ; extra == "tests"
Project-URL: Discussions, https://github.com/ansys/pychemkin/discussions
Project-URL: Documentation, https://chemkin.docs.pyansys.com/
Project-URL: Issues, https://github.com/ansys/pychemkin/issues
Project-URL: Releases, https://github.com/ansys/pychemkin/releases/
Project-URL: Source, https://github.com/ansys/pychemkin
Provides-Extra: doc
Provides-Extra: tests
